[{"class_name": "motorbike", "bbox": "29 210 305 400", "used": false}, {"class_name": "motorbike", "bbox": "188 209 415 401", "used": false}, {"class_name": "person", "bbox": "103 161 167 235", "used": false}, {"class_name": "person", "bbox": "3 165 65 235", "used": false}, {"class_name": "person", "bbox": "287 176 324 232", "used": false}, {"class_name": "person", "bbox": "332 171 381 232", "used": false}, {"class_name": "person", "bbox": "142 122 200 210", "used": false}, {"class_name": "person", "bbox": "190 114 237 212", "used": false}, {"class_name": "person", "bbox": "286 105 336 209", "used": false}, {"class_name": "person", "bbox": "253 111 290 171", "used": false}, {"class_name": "person", "bbox": "252 174 329 261", "used": false}, {"class_name": "handbag", "bbox": "198 148 230 201", "used": false}, {"class_name": "bottle", "bbox": "244 67 253 98", "used": false}, {"class_name": "bottle", "bbox": "297 68 304 90", "used": false}, {"class_name": "cup", "bbox": "271 152 279 170", "used": false}, {"class_name": "chair", "bbox": "255 216 319 263", "used": false}, {"class_name": "chair", "bbox": "332 198 345 223", "used": false}, {"class_name": "chair", "bbox": "377 216 416 344", "used": false}, {"class_name": "chair", "bbox": "160 208 180 232", "used": false}, {"class_name": "chair", "bbox": "0 208 41 254", "used": false}, {"class_name": "potted_plant", "bbox": "74 207 100 239", "used": false}, {"class_name": "vase", "bbox": "255 145 263 163", "used": false}, {"class_name": "person", "bbox": "171 170 213 242", "used": false}, {"class_name": "motorbike", "bbox": "0 238 83 410", "used": false}, {"class_name": "bottle", "bbox": "290 68 297 87", "used": false}, {"class_name": "bottle", "bbox": "282 70 290 88", "used": false}, {"class_name": "bottle", "bbox": "268 73 275 98", "used": false}, {"class_name": "bottle", "bbox": "260 73 268 98", "used": false}, {"class_name": "bottle", "bbox": "252 67 259 98", "used": false}, {"class_name": "bottle", "bbox": "238 70 245 98", "used": false}, {"class_name": "bottle", "bbox": "209 68 216 98", "used": false}, {"class_name": "bottle", "bbox": "201 70 209 98", "used": false}, {"class_name": "bottle", "bbox": "224 69 230 99", "used": false}, {"class_name": "bottle", "bbox": "162 94 171 122", "used": false}, {"class_name": "dining_table", "bbox": "227 162 304 199", "used": false}, {"class_name": "dining_table", "bbox": "119 233 139 241", "used": false}, {"class_name": "person", "bbox": "382 173 416 217", "used": false}, {"class_name": "cup", "bbox": "252 149 259 171", "used": false}, {"class_name": "cup", "bbox": "71 201 79 230", "used": false}]