[{"class_name": "bird", "bbox": "112 231 129 243", "used": false}, {"class_name": "bird", "bbox": "318 197 337 213", "used": false}, {"class_name": "bird", "bbox": "229 208 244 220", "used": false}, {"class_name": "bird", "bbox": "338 166 351 184", "used": false}, {"class_name": "bird", "bbox": "375 191 388 195", "used": false}, {"class_name": "bird", "bbox": "391 199 406 217", "used": false}, {"class_name": "boat", "bbox": "356 292 369 306", "used": false}, {"class_name": "boat", "bbox": "393 295 399 307", "used": false}, {"class_name": "boat", "bbox": "243 288 254 292", "used": false}, {"class_name": "bird", "bbox": "56 244 70 264", "used": false}, {"class_name": "bird", "bbox": "282 253 303 272", "used": false}, {"class_name": "bird", "bbox": "378 186 385 191", "used": false}, {"class_name": "clock", "bbox": "43 95 59 117", "used": false}, {"class_name": "boat", "bbox": "347 298 355 306", "used": false}]