[{"class_name": "dog", "bbox": "192 259 269 343", "used": false}, {"class_name": "potted_plant", "bbox": "299 127 389 260", "used": false}, {"class_name": "chair", "bbox": "231 122 316 249", "used": false}, {"class_name": "sports_ball", "bbox": "132 294 139 304", "used": false}, {"class_name": "sports_ball", "bbox": "139 323 147 332", "used": false}, {"class_name": "bottle", "bbox": "291 385 304 415", "used": false}, {"class_name": "bottle", "bbox": "329 365 343 405", "used": false}, {"class_name": "bed", "bbox": "191 246 275 368", "used": false}, {"class_name": "vase", "bbox": "356 204 371 231", "used": false}]