[{"class_name": "tvmonitor", "bbox": "98 104 207 263", "used": false}, {"class_name": "cup", "bbox": "145 326 172 375", "used": false}, {"class_name": "spoon", "bbox": "85 333 111 358", "used": false}, {"class_name": "laptop", "bbox": "204 124 292 224", "used": false}, {"class_name": "keyboard", "bbox": "173 257 272 325", "used": false}, {"class_name": "potted_plant", "bbox": "81 96 161 194", "used": false}, {"class_name": "keyboard", "bbox": "211 191 275 208", "used": false}, {"class_name": "person", "bbox": "347 103 361 121", "used": false}, {"class_name": "cup", "bbox": "81 291 110 334", "used": false}, {"class_name": "cup", "bbox": "115 291 143 339", "used": false}, {"class_name": "mouse", "bbox": "171 312 193 338", "used": false}]