[{"confidence": "0.991603", "file_id": "126", "bbox": "70 0 162 78"}, {"confidence": "0.972925", "file_id": "120", "bbox": "71 24 137 184"}, {"confidence": "0.955736", "file_id": "168", "bbox": "327 8 416 186"}, {"confidence": "0.952709", "file_id": "65", "bbox": "145 327 172 373"}, {"confidence": "0.877027", "file_id": "300", "bbox": "178 20 372 252"}, {"confidence": "0.875084", "file_id": "120", "bbox": "159 4 217 159"}, {"confidence": "0.860037", "file_id": "136", "bbox": "46 32 150 132"}, {"confidence": "0.827351", "file_id": "140", "bbox": "247 286 269 331"}, {"confidence": "0.825875", "file_id": "201", "bbox": "321 260 366 331"}, {"confidence": "0.788841", "file_id": "48", "bbox": "287 145 343 228"}, {"confidence": "0.723575", "file_id": "182", "bbox": "164 293 185 329"}, {"confidence": "0.692261", "file_id": "261", "bbox": "216 262 241 338"}, {"confidence": "0.660388", "file_id": "261", "bbox": "153 216 171 256"}, {"confidence": "0.648212", "file_id": "9", "bbox": "139 311 155 345"}, {"confidence": "0.645204", "file_id": "83", "bbox": "115 2 184 114"}, {"confidence": "0.641115", "file_id": "127", "bbox": "2 199 68 334"}, {"confidence": "0.583195", "file_id": "91", "bbox": "18 109 35 137"}, {"confidence": "0.582104", "file_id": "296", "bbox": "205 227 247 297"}, {"confidence": "0.570068", "file_id": "280", "bbox": "68 152 176 219"}, {"confidence": "0.550004", "file_id": "134", "bbox": "164 1 257 47"}, {"confidence": "0.526067", "file_id": "280", "bbox": "216 9 315 73"}, {"confidence": "0.524214", "file_id": "297", "bbox": "56 4 150 78"}, {"confidence": "0.50831", "file_id": "293", "bbox": "207 334 226 358"}, {"confidence": "0.496593", "file_id": "107", "bbox": "183 280 238 411"}, {"confidence": "0.454796", "file_id": "41", "bbox": "380 63 397 106"}, {"confidence": "0.450476", "file_id": "136", "bbox": "18 20 145 271"}, {"confidence": "0.443204", "file_id": "201", "bbox": "214 251 261 298"}, {"confidence": "0.436222", "file_id": "2", "bbox": "322 165 416 303"}, {"confidence": "0.426455", "file_id": "201", "bbox": "203 217 227 248"}, {"confidence": "0.409953", "file_id": "218", "bbox": "155 284 173 314"}, {"confidence": "0.409185", "file_id": "127", "bbox": "289 235 407 365"}, {"confidence": "0.404461", "file_id": "91", "bbox": "29 111 45 136"}, {"confidence": "0.400996", "file_id": "65", "bbox": "115 295 142 350"}, {"confidence": "0.399502", "file_id": "201", "bbox": "170 234 210 297"}, {"confidence": "0.385183", "file_id": "33", "bbox": "4 5 152 162"}, {"confidence": "0.379043", "file_id": "182", "bbox": "66 242 84 280"}, {"confidence": "0.371296", "file_id": "9", "bbox": "116 325 133 372"}, {"confidence": "0.369024", "file_id": "218", "bbox": "133 280 148 309"}, {"confidence": "0.35747", "file_id": "261", "bbox": "212 171 226 220"}, {"confidence": "0.355052", "file_id": "91", "bbox": "0 100 14 137"}, {"confidence": "0.339028", "file_id": "201", "bbox": "138 216 168 243"}, {"confidence": "0.33754", "file_id": "216", "bbox": "288 380 308 406"}, {"confidence": "0.335125", "file_id": "167", "bbox": "294 229 397 320"}, {"confidence": "0.315378", "file_id": "218", "bbox": "0 276 13 319"}, {"confidence": "0.314663", "file_id": "288", "bbox": "145 269 175 301"}, {"confidence": "0.290286", "file_id": "140", "bbox": "240 292 260 327"}, {"confidence": "0.251222", "file_id": "201", "bbox": "137 204 166 232"}, {"confidence": "0.21713", "file_id": "79", "bbox": "273 254 295 274"}, {"confidence": "0.216632", "file_id": "293", "bbox": "189 335 203 382"}, {"confidence": "0.214456", "file_id": "261", "bbox": "221 240 246 265"}, {"confidence": "0.209234", "file_id": "167", "bbox": "282 229 402 395"}, {"confidence": "0.19888", "file_id": "89", "bbox": "254 6 297 64"}, {"confidence": "0.191553", "file_id": "41", "bbox": "401 66 415 111"}, {"confidence": "0.190206", "file_id": "56", "bbox": "95 368 119 394"}, {"confidence": "0.183862", "file_id": "280", "bbox": "183 14 243 132"}, {"confidence": "0.181931", "file_id": "92", "bbox": "283 182 306 217"}, {"confidence": "0.178866", "file_id": "59", "bbox": "82 182 98 212"}, {"confidence": "0.178061", "file_id": "92", "bbox": "303 210 323 249"}, {"confidence": "0.176742", "file_id": "58", "bbox": "177 376 199 409"}, {"confidence": "0.174938", "file_id": "293", "bbox": "126 321 142 358"}, {"confidence": "0.158565", "file_id": "127", "bbox": "10 257 51 333"}, {"confidence": "0.156519", "file_id": "287", "bbox": "16 271 79 355"}, {"confidence": "0.154672", "file_id": "22", "bbox": "329 250 353 281"}, {"confidence": "0.149166", "file_id": "92", "bbox": "300 183 325 214"}, {"confidence": "0.140033", "file_id": "9", "bbox": "92 321 111 370"}, {"confidence": "0.137128", "file_id": "107", "bbox": "166 384 194 416"}, {"confidence": "0.136919", "file_id": "163", "bbox": "85 203 124 253"}, {"confidence": "0.135956", "file_id": "293", "bbox": "142 328 160 359"}, {"confidence": "0.135053", "file_id": "218", "bbox": "212 282 228 312"}, {"confidence": "0.132129", "file_id": "9", "bbox": "131 306 147 341"}, {"confidence": "0.131719", "file_id": "130", "bbox": "1 287 34 336"}, {"confidence": "0.127627", "file_id": "270", "bbox": "286 231 308 254"}, {"confidence": "0.123276", "file_id": "59", "bbox": "114 174 130 203"}, {"confidence": "0.121371", "file_id": "29", "bbox": "110 181 131 206"}, {"confidence": "0.11822", "file_id": "130", "bbox": "117 301 147 319"}, {"confidence": "0.117525", "file_id": "86", "bbox": "170 376 234 415"}, {"confidence": "0.112629", "file_id": "201", "bbox": "138 233 169 257"}, {"confidence": "0.112581", "file_id": "261", "bbox": "223 178 234 225"}, {"confidence": "0.109654", "file_id": "56", "bbox": "223 286 239 307"}, {"confidence": "0.107933", "file_id": "261", "bbox": "269 201 282 235"}, {"confidence": "0.103733", "file_id": "201", "bbox": "158 196 180 233"}, {"confidence": "0.103678", "file_id": "65", "bbox": "80 277 109 337"}, {"confidence": "0.0977513", "file_id": "130", "bbox": "55 274 85 340"}, {"confidence": "0.0944972", "file_id": "79", "bbox": "255 239 268 277"}, {"confidence": "0.0939979", "file_id": "266", "bbox": "160 213 174 250"}, {"confidence": "0.0910658", "file_id": "70", "bbox": "395 379 415 410"}, {"confidence": "0.0872889", "file_id": "294", "bbox": "16 124 129 409"}, {"confidence": "0.0861856", "file_id": "201", "bbox": "219 223 243 246"}, {"confidence": "0.0861202", "file_id": "113", "bbox": "70 207 130 336"}, {"confidence": "0.0855278", "file_id": "201", "bbox": "97 286 130 301"}, {"confidence": "0.0849229", "file_id": "261", "bbox": "143 217 162 254"}, {"confidence": "0.0809138", "file_id": "91", "bbox": "11 68 32 85"}, {"confidence": "0.0785578", "file_id": "218", "bbox": "55 235 84 323"}, {"confidence": "0.0784994", "file_id": "91", "bbox": "401 296 416 329"}, {"confidence": "0.0781709", "file_id": "281", "bbox": "97 198 120 259"}, {"confidence": "0.0781204", "file_id": "9", "bbox": "97 335 112 376"}, {"confidence": "0.0742335", "file_id": "293", "bbox": "176 358 192 386"}, {"confidence": "0.0715118", "file_id": "261", "bbox": "157 250 178 281"}, {"confidence": "0.0714571", "file_id": "293", "bbox": "209 305 226 349"}, {"confidence": "0.0697757", "file_id": "92", "bbox": "274 183 292 214"}, {"confidence": "0.0668984", "file_id": "107", "bbox": "126 230 149 260"}, {"confidence": "0.0666556", "file_id": "261", "bbox": "218 288 236 337"}, {"confidence": "0.0642901", "file_id": "293", "bbox": "189 327 206 364"}, {"confidence": "0.0633418", "file_id": "293", "bbox": "210 298 226 326"}, {"confidence": "0.0623665", "file_id": "70", "bbox": "137 342 155 371"}, {"confidence": "0.06207", "file_id": "189", "bbox": "385 198 399 240"}, {"confidence": "0.0604382", "file_id": "201", "bbox": "152 216 175 248"}, {"confidence": "0.0594639", "file_id": "22", "bbox": "336 256 359 293"}, {"confidence": "0.059388", "file_id": "130", "bbox": "32 299 52 330"}, {"confidence": "0.058428", "file_id": "31", "bbox": "334 0 415 88"}, {"confidence": "0.0575642", "file_id": "201", "bbox": "157 186 182 215"}, {"confidence": "0.0570384", "file_id": "263", "bbox": "169 303 187 344"}, {"confidence": "0.0559924", "file_id": "29", "bbox": "72 184 92 209"}, {"confidence": "0.0552397", "file_id": "248", "bbox": "228 62 294 170"}, {"confidence": "0.0550806", "file_id": "9", "bbox": "122 321 139 368"}, {"confidence": "0.0550413", "file_id": "293", "bbox": "189 358 202 387"}, {"confidence": "0.0547931", "file_id": "201", "bbox": "216 233 248 258"}, {"confidence": "0.0535467", "file_id": "31", "bbox": "1 0 79 79"}, {"confidence": "0.0534919", "file_id": "3", "bbox": "1 111 38 198"}, {"confidence": "0.0521825", "file_id": "280", "bbox": "181 5 313 146"}, {"confidence": "0.0519144", "file_id": "130", "bbox": "91 292 113 324"}, {"confidence": "0.0518786", "file_id": "282", "bbox": "121 249 146 277"}, {"confidence": "0.0515219", "file_id": "134", "bbox": "153 1 183 25"}, {"confidence": "0.0515147", "file_id": "261", "bbox": "126 214 146 247"}, {"confidence": "0.0513981", "file_id": "112", "bbox": "316 0 414 29"}, {"confidence": "0.0506636", "file_id": "280", "bbox": "184 115 224 161"}]