[{"confidence": "0.951861", "file_id": "76", "bbox": "360 74 413 266"}, {"confidence": "0.900232", "file_id": "102", "bbox": "92 134 236 413"}, {"confidence": "0.893773", "file_id": "207", "bbox": "141 183 209 372"}, {"confidence": "0.830916", "file_id": "207", "bbox": "188 166 308 376"}, {"confidence": "0.765829", "file_id": "76", "bbox": "80 33 163 387"}, {"confidence": "0.74609", "file_id": "251", "bbox": "49 81 416 397"}, {"confidence": "0.581087", "file_id": "76", "bbox": "140 32 332 391"}, {"confidence": "0.154777", "file_id": "251", "bbox": "46 0 374 298"}]